multi_quantization/__init__.py
multi_quantization/checkpoint.py
multi_quantization/prediction.py
multi_quantization/quantization.py
multi_quantization-0.1.1.dist-info/METADATA
multi_quantization-0.1.1.dist-info/WHEEL
multi_quantization-0.1.1.dist-info/top_level.txt
multi_quantization-0.1.1.dist-info/RECORD
