Metadata-Version: 2.1
Name: multi-quantization
Version: 0.1.1
Summary: Utility for learning compact codes for vectors, based on Torch
Home-page: https://github.com/k2-fsa/multi_quantization
Author: Daniel Povey
Author-email: dpovey@gmail.com
License: Apache-2.0 License
Platform: UNKNOWN
Classifier: Development Status :: 3 - Alpha
Classifier: Programming Language :: Python :: 3.6
Classifier: Programming Language :: Python :: 3.7
Classifier: Programming Language :: Python :: 3.8
Classifier: Intended Audience :: Science/Research
Classifier: Operating System :: POSIX :: Linux
Classifier: License :: OSI Approved :: Apache Software License
Classifier: Topic :: Scientific/Engineering :: Artificial Intelligence
Classifier: Topic :: Software Development :: Libraries :: Python Modules
Classifier: Typing :: Typed
Requires-Python: >=3.6.0
Requires-Dist: torch
Requires-Dist: numpy
Requires-Dist: h5py
